fifo.v
module fifo (
    input clk,
    input rst,
    input wr_en,
    input rd_en,
    input [7:0] din,
    output reg [7:0] dout,
    output full,
    output empty
);

reg [7:0] mem [0:15];
reg [3:0] wr_ptr, rd_ptr;
reg [4:0] count;

assign full  = (count == 16);
assign empty = (count == 0);

always @(posedge clk or posedge rst) begin
    if (rst) begin
        wr_ptr <= 0;
        rd_ptr <= 0;
        count  <= 0;
        dout   <= 0;
    end else begin
        if (wr_en && !full) begin
            mem[wr_ptr] <= din;
            wr_ptr <= wr_ptr + 1;
            count <= count + 1;
        end
        if (rd_en && !empty) begin
            dout <= mem[rd_ptr];
            rd_ptr <= rd_ptr + 1;
            count <= count - 1;
        end
    end
end
endmodule

tb_fifo.v
module tb_fifo;
reg clk, rst, wr_en, rd_en;
reg [7:0] din;
wire [7:0] dout;
wire full, empty;

fifo uut (.clk(clk),.rst(rst),.wr_en(wr_en),
    .rd_en(rd_en),.din(din),.dout(dout),
    .full(full),.empty(empty));

always #5 clk = ~clk;

initial begin
    $dumpfile("fifo.vcd");
    $dumpvars(0, tb_fifo);
    clk=0; rst=1; wr_en=0; rd_en=0; din=0;
    #20 rst=0;
    
    // Write data
    wr_en=1;
    din=8'hAA; #10;
    din=8'hBB; #10;
    din=8'hCC; #10;
    din=8'hDD; #10;
    wr_en=0;
    
    // Read data
    #10 rd_en=1;
    #10; #10; #10; #10;
    rd_en=0;
    
    #20;
    $display("Full: %b, Empty: %b", full, empty);
    $display("Last dout: %h", dout);
    $finish;
end
endmodule

fifo.vcd
$date
	Tue Jun 30 05:06:57 2026
$end
$version
	Icarus Verilog
$end
$timescale
	1s
$end
$scope module tb_fifo $end
$var wire 1 ! full $end
$var wire 1 " empty $end
$var wire 8 # dout [7:0] $end
$var reg 1 $ clk $end
$var reg 8 % din [7:0] $end
$var reg 1 & rd_en $end
$var reg 1 ' rst $end
$var reg 1 ( wr_en $end
$scope module uut $end
$var wire 1 $ clk $end
$var wire 8 ) din [7:0] $end
$var wire 1 & rd_en $end
$var wire 1 ' rst $end
$var wire 1 ( wr_en $end
$var wire 1 ! full $end
$var wire 1 " empty $end
$var reg 5 * count [4:0] $end
$var reg 8 + dout [7:0] $end
$var reg 4 , rd_ptr [3:0] $end
$var reg 4 - wr_ptr [3:0] $end
$upscope $end
$upscope $end
$enddefinitions $end
$comment Show the parameter values. $end
$dumpall
$end
#0
$dumpvars
b0 -
b0 ,
b0 +
b0 *
b0 )
0(
1'
0&
b0 %
0$
b0 #
1"
0!
$end
#5
1$
#10
0$
#15
1$
#20
0$
b10101010 %
b10101010 )
1(
0'
#25
0"
b1 *
b1 -
1$
#30
0$
b10111011 %
b10111011 )
#35
b10 *
b10 -
1$
#40
0$
b11001100 %
b11001100 )
#45
b11 *
b11 -
1$
#50
0$
b11011101 %
b11011101 )
#55
b100 *
b100 -
1$
#60
0$
0(
#65
1$
#70
0$
1&
#75
b11 *
b1 ,
b10101010 #
b10101010 +
1$
#80
0$
#85
b10 *
b10 ,
b10111011 #
b10111011 +
1$
#90
0$
#95
b1 *
b11 ,
b11001100 #
b11001100 +
1$
#100
0$
#105
1"
b0 *
b100 ,
b11011101 #
b11011101 +
1$
#110
0$
0&
